CHANGES.txt
README.txt
buildout.cfg
setup.py
bootstrap/bootstrap.py
src/zc/__init__.py
src/zc.twist.egg-info/PKG-INFO
src/zc.twist.egg-info/SOURCES.txt
src/zc.twist.egg-info/dependency_links.txt
src/zc.twist.egg-info/not-zip-safe
src/zc.twist.egg-info/requires.txt
src/zc.twist.egg-info/top_level.txt
src/zc/twist/README.txt
src/zc/twist/__init__.py
src/zc/twist/_methodwrapper.c
src/zc/twist/tests.py