Metadata-Version: 1.0
Name: zc.twist
Version: 1.1
Summary: Mixing Twisted and ZODB
